BCI2000Tools/AllTools.py
BCI2000Tools/Bootstrapping.py
BCI2000Tools/Chain.py
BCI2000Tools/Container.py
BCI2000Tools/ElectrodeGrids.py
BCI2000Tools/ElectrodePositions.py
BCI2000Tools/Electrodes.py
BCI2000Tools/EventRelated.py
BCI2000Tools/Expressions.py
BCI2000Tools/FileReader.py
BCI2000Tools/LoadStream2Mat.py
BCI2000Tools/Numerics.py
BCI2000Tools/Parameters.py
BCI2000Tools/Plotting.py
BCI2000Tools/Remote.py
BCI2000Tools/TimingAnalysis.py
BCI2000Tools/__init__.py
bci2000tools-1.1.0.dist-info/METADATA
bci2000tools-1.1.0.dist-info/WHEEL
bci2000tools-1.1.0.dist-info/top_level.txt
bci2000tools-1.1.0.dist-info/RECORD
