Metadata-Version: 2.4
Name: BCI2000Tools
Version: 1.1.0
Summary: A suite of Python tools for working with BCI2000 data files, processing chains, and live sessions
Home-page: https://bci2000.org
License: GPL v3+
Requires-Dist: numpy
Dynamic: description
Dynamic: description-content-type
Dynamic: home-page
Dynamic: license
Dynamic: requires-dist
Dynamic: summary
